libreselery/__init__.py
libreselery/coinbase_connector.py
libreselery/collection_utils.py
libreselery/commandline.py
libreselery/commit_identifier.py
libreselery/configuration.py
libreselery/git_utils.py
libreselery/github_connector.py
libreselery/librariesio_connector.py
libreselery/libreselery.py
libreselery/os_utils.py
libreselery/selery_utils.py
libreselery/visualization.py
libreselery-0.0.1.dev74.data/data/libreselery/ruby_extensions/scan.rb
libreselery-0.0.1.dev74.data/scripts/selery
libreselery-0.0.1.dev74.dist-info/LICENSE
libreselery-0.0.1.dev74.dist-info/METADATA
libreselery-0.0.1.dev74.dist-info/WHEEL
libreselery-0.0.1.dev74.dist-info/dependency_links.txt
libreselery-0.0.1.dev74.dist-info/top_level.txt
libreselery-0.0.1.dev74.dist-info/RECORD
