Metadata-Version: 2.1
Name: libreselery
Version: 0.0.1.dev74
Summary: A Software-Defined Funding Distribution
Home-page: https://github.com/protontypes/libreselery
License: UNKNOWN
Platform: UNKNOWN
Requires-Dist: pygithub (==1.52)
Requires-Dist: dnspython (==2.0.0)
Requires-Dist: pyyaml (==5.3.1)
Requires-Dist: coinbase
Requires-Dist: gitpython (==3.1.7)
Requires-Dist: pybraries (==0.2.2)
Requires-Dist: urlextract (==1.0.0)
Requires-Dist: matplotlib (==3.3.0)
Requires-Dist: numpy (==1.19.1)
Requires-Dist: qrcode
Requires-Dist: wheel
